MANIFEST.in
README.rst
setup.cfg
setup.py
tissue.py
tissue.egg-info/PKG-INFO
tissue.egg-info/SOURCES.txt
tissue.egg-info/dependency_links.txt
tissue.egg-info/entry_points.txt
tissue.egg-info/requires.txt
tissue.egg-info/top_level.txt