Metadata-Version: 1.0
Name: tissue
Version: 0.9.2
Summary: Tissue - automated pep8 checker for nose
Home-page: https://github.com/WoLpH/tissue
Author: Jason Kölker & Rick van Hattem
Author-email: rick@wol.ph
License: GNU LGPL
Keywords: pep8 nose
Platform: UNKNOWN
